AUTHORS
LICENSE
MANIFEST.in
README.rst
RELEASE-VERSION
setup.py
docs/cmdline.rst
docs/index.rst
docs/installation.rst
docs/overview.rst
docs/toc.rst
docs/usage.rst
examples/system_summary.py
gitpy_versioning/__init__.py
steelscript/__init__.py
steelscript.cmdline.egg-info/PKG-INFO
steelscript.cmdline.egg-info/SOURCES.txt
steelscript.cmdline.egg-info/dependency_links.txt
steelscript.cmdline.egg-info/namespace_packages.txt
steelscript.cmdline.egg-info/requires.txt
steelscript.cmdline.egg-info/top_level.txt
steelscript/cmdline/__init__.py
steelscript/cmdline/channel.py
steelscript/cmdline/exceptions.py
steelscript/cmdline/libvirtchannel.py
steelscript/cmdline/parsers.py
steelscript/cmdline/shell.py
steelscript/cmdline/sshchannel.py
steelscript/cmdline/sshprocess.py
steelscript/cmdline/telnetchannel.py
steelscript/cmdline/transport.py
steelscript/cmdline/cli/__init__.py
steelscript/cmdline/cli/ios_cli.py
steelscript/cmdline/cli/rvbd_cli.py
steelscript/cmdline/cli/vyatta_cli.py