Metadata-Version: 2.1
Name: steelscript.cmdline
Version: 2.0
Summary: SteelScript support for command-line interaction
Home-page: http://pythonhosted.org/steelscript
Author: Riverbed Technology
Author-email: eng-github@riverbed.com
License: MIT
Platform: Linux
Platform: Mac OS
Platform: Windows
Classifier: Development Status :: 4 - Beta
Classifier: Intended Audience :: Developers
Classifier: Intended Audience :: Information Technology
Classifier: Intended Audience :: System Administrators
Classifier: License :: OSI Approved :: MIT License
Classifier: Programming Language :: Python :: 3.6
Classifier: Programming Language :: Python :: 3.7
Classifier: Topic :: System :: Networking
Provides-Extra: dev
Provides-Extra: doc
Provides-Extra: all
Provides-Extra: test
